{"hash":"c815fb54cce91fc24cdd0806968af98624d603e5","data":{"tag":{"title":"Linux","belongsTo":{"totalCount":1,"pageInfo":{"totalPages":1,"currentPage":1},"edges":[{"node":{"title":"How to execute terminal commands with your voice on Linux","timeToRead":5,"date":"June 1, 2020","path":"/execute-commands-with-voice","summary":"Proof of concept use of the open source NLP tool 'voice2json' to execute arbitrary commands in a linux terminal","tags":[{"title":"Bash"},{"title":"Linux"},{"title":"Ubuntu"},{"title":"AI"},{"title":"NLP"},{"title":"Open Source"}]}}]}}},"context":{}}